cldpy/__init__.py
cldpy/numpy/__init__.py
cldpy/numpy/monkey_patch.py
cldpy/pandas/__init__.py
npc_internal/__init__.py
npc_internal/config.py
npc_internal/logger.py
npc_internal/monkey_patch.py
npc_internal/protocol.py
npc_internal/proxy.py
npc_internal/proxy_objects.py
npc_internal/test_monkey_patch.py
npc_internal/util.py
npc_internal/server/__init__.py
npc_internal/server/server.py
npc_internal/server/test.py
test_util/__init__.py
test_util/util.py
tests/__init__.py
tests/test_from_numpy.py
tests/test_from_numpy_2.py
tests/test_monkey_patch.py
tests/from_numpy/__init__.py
tests/from_numpy/test_multiarray.py
tests/from_numpy/test_nditer.py
tests/from_numpy/compat/__init__.py
tests/from_numpy/compat/tests/__init__.py
tests/from_numpy/compat/tests/test_compat.py
tests/from_numpy/core/__init__.py
tests/from_numpy/core/tests/__init__.py
tests/from_numpy/core/tests/test_abc.py
tests/from_numpy/core/tests/test_api.py
tests/from_numpy/core/tests/test_arrayprint.py
tests/from_numpy/core/tests/test_datetime.py
tests/from_numpy/core/tests/test_defchararray.py
tests/from_numpy/core/tests/test_deprecations.py
tests/from_numpy/core/tests/test_dtype.py
tests/from_numpy/core/tests/test_einsum.py
tests/from_numpy/core/tests/test_errstate.py
tests/from_numpy/core/tests/test_extint128.py
tests/from_numpy/core/tests/test_function_base.py
tests/from_numpy/core/tests/test_getlimits.py
tests/from_numpy/core/tests/test_half.py
tests/from_numpy/core/tests/test_indexerrors.py
tests/from_numpy/core/tests/test_indexing.py
tests/from_numpy/core/tests/test_item_selection.py
tests/from_numpy/core/tests/test_longdouble.py
tests/from_numpy/core/tests/test_machar.py
tests/from_numpy/core/tests/test_mem_overlap.py
tests/from_numpy/core/tests/test_memmap.py
tests/from_numpy/core/tests/test_multiarray.py
tests/from_numpy/core/tests/test_nditer.py
tests/from_numpy/core/tests/test_numeric.py
tests/from_numpy/core/tests/test_numerictypes.py
tests/from_numpy/core/tests/test_overrides.py
cldpy-0.0.14.dist-info/LICENSE
cldpy-0.0.14.dist-info/METADATA
cldpy-0.0.14.dist-info/WHEEL
cldpy-0.0.14.dist-info/top_level.txt
cldpy-0.0.14.dist-info/RECORD
